LICENSE
MANIFEST.in
README.rst
setup.py
django_menuz.egg-info/PKG-INFO
django_menuz.egg-info/SOURCES.txt
django_menuz.egg-info/dependency_links.txt
django_menuz.egg-info/not-zip-safe
django_menuz.egg-info/top_level.txt
menuz/__init__.py
menuz/admin.py
menuz/forms.py
menuz/models.py
menuz/registry.py
menuz/urls.py
menuz/utils.py
menuz/views.py
menuz/static/admin/menuz/css/menuz.css
menuz/static/admin/menuz/images/icons.png
menuz/static/admin/menuz/images/loading.gif
menuz/static/admin/menuz/js/jquery-1.7.1.min.js
menuz/static/admin/menuz/js/jquery-ui-1.8.17.custom.min.js
menuz/static/admin/menuz/js/jquery.mjs.nestedSortable.js
menuz/static/admin/menuz/js/menuz.js
menuz/templates/admin/menuz/menuz/change_form.html
menuz/templates/admin/menuz/menuz/menu_builder.html
menuz/templates/admin/menuz/menuz/menu_item.html
menuz/templatetags/__init__.py
menuz/templatetags/menuz_tags.py
menuz/tests/__init__.py
menuz/tests/test_template_tags.py
menuz/tests/test_utils.py
menuz/tests/test_views.py