Metadata-Version: 1.1
Name: django-menuz
Version: 2.0.0
Summary: Drag and drop menu manager for Django.
Home-page: https://github.com/ekaputra07/django-menuz
Author: Eka Putra
Author-email: ekaputra@balitechy.com
License: BSD
Download-URL: https://github.com/ekaputra07/django-menuz/releases
Platform: UNKNOWN
Classifier: Development Status :: 4 - Beta
Classifier: Framework :: Django
Classifier: Intended Audience :: Developers
Classifier: License :: OSI Approved :: BSD License
Classifier: Operating System :: OS Independent
Classifier: Programming Language :: Python
Classifier: Topic :: Internet :: WWW/HTTP
